{
    "magcord_guild_id": null,
    "boost_logs_channel_id": null,
    "oauth_boost_logs_channel_id": null,
    "user_ping_scan_channel_id": null,
    "role_ping_scan_channel_id": null,
    "embed_mode_channel_id": null,
    "wallets_channel_id": null,
    "commands_logs_channel_id": null,
    "server_logs_channel_id": null,
    "relationship_logs_channel_id": null,
    "gc_logs_channel_id": null,
    "giveaway_sniper_channel_id": null,
    "server_msgs_sniper_channel_id": null,
    "dm_msgs_sniper_channel_id": null,
    "gc_msgs_sniper_channel_id": null,
    "server_edit_sniper_channel_id": null,
    "dm_edit_sniper_channel_id": null,
    "gc_edit_sniper_channel_id": null
}